reporter_google_ads_dn
