Metadata-Version: 2.1
Name: reporter-google-ads-dn
Version: 0.2
Summary: Google ads reporter
License: UNKNOWN
Platform: UNKNOWN
